Workbook

Sheet 00 Read Me
A1: Enterprise Architecture Project Impact Matrix
A2: Fernwood Distribution Ltd, cloud portfolio (TEST SCENARIO) | Version 1.0 | 2026-03-09
A4: Purpose
A5: Ranks five proposed cloud initiatives for a first funding tranche of up to 150,000 USD, weighted for run cost as the CFO instructed on 2026-03-02.
A6: All names and figures are fictional test data.
A7: Every score is a starting position for review, not a decision.
A9: Sheets
A10: Sheet | B10: What it is for | C10: Who maintains it | D10: Update cadence
A11: 01 Scoring Model | B11: Weights and the 1 to 5 anchors. Change a weight and every project score recalculates. | C11: Enterprise Architecture | D11: At each portfolio review
A12: 02 Portfolio Summary | B12: Roll-up with weighted score, rank, cost and score per $100k. The board view. | C12: Enterprise Architecture | D12: Automatic
A13: 03 Sequencing | B13: Waves, cross-project dependencies, and resource contention. | C13: EA and Delivery | D13: At each portfolio review
A14: 04 Risk Register | B14: All project risks with likelihood, impact and mitigation. | C14: Enterprise Architecture | D14: Fortnightly
A15: 05 Open Questions | B15: What must be answered before approval, and the decision each blocks. | C15: Engagement lead | D15: Weekly until closed
A16: 06 Savings Case | B16: Payback model. Fill the baseline and expected saving; payback calculates. | C16: FinOps and EA | D16: Monthly
A17: 07 Decision Log | B17: What the forum decided, on what conditions, and who answers for it. | C17: EA and Delivery | D17: After each forum
A18: P1 to P8 | B18: One sheet per initiative. Delete the slots you do not use. | C18: Project architect | D18: Weekly during delivery
A20: Cell conventions
A21: Blue text | B21: Hardcoded input. Edit these.
A22: Green text | B22: Link pulled from another sheet. Do not overwrite.
A23: Black text | B23: Calculated. Do not overwrite.
A24: Yellow fill | B24: Information still owed. These are the gaps that block approval.
A26: Rules that keep this useful
A27: Never give two initiatives the same score profile. If they score the same on every dimension, the matrix cannot rank them and has no decision value. This is the single most common failure mode.
A28: Score against evidence, and cite the source document and section in the evidence column. A score of 3 with a named source beats a score of 5 with none.
A29: Where no evidence exists, score conservatively and log the gap on '05 Open Questions'. Do not guess upward.
A30: A score can be deliberately low where a proposal is weaker than it claims. Those are the most valuable cells in the workbook.
A31: Set the weights to the prioritization lens the sponsor confirms, before scoring. Do not score first and pick the lens that gives the answer you wanted.
A32: Owners are people, not roles. 'Security' does not approve anything; a named individual does.
A34: Governance record
A35: Prioritization lens | B35: run_cost | C35: Confirmed with the sponsor before scoring.
A36: Lens agreed by (named) | B36: Dana Whitcombe, CFO | C36: The person who accepted these weights.
A37: Lens agreed on | B37: 2026-03-02
A38: Risk appetite | B38: No risk scoring 9 or above goes forward without a named owner. | C38: Red risks start at a score of 9.
A39: Next review | B39: 2026-06-01 | C39: Re-score on a material change, or on this date.
A40: Terms follow TOGAF and COBIT: an initiative is a work package, a wave is a transition architecture. See references/standards-mapping.md.
A42: Document coverage
A43: Document | B43: What it feeds in this workbook | C43: Level | D43: Coverage
A44: Proposal, business case or statement of work (PROPOSAL) | B44: Project profile (name, sponsor, scope, deadline, status, basis); Business value and Cost assessments; the questions the proposal asks the client go to 05 Open Questions | C44: Required, each initiative | D44: Received for all scored initiatives
A45: Cost and effort estimate: line items, hours by role, duration (ESTIMATE) | B45: Cost and duration cells, score per $100k on 02 Portfolio Summary, capacity on 03 Sequencing, Delivery confidence | C45: Required, each initiative | D45: Received for all scored initiatives
A46: Target-state architecture, principles and strategy (TARGET_STATE) | B46: Strategic alignment score, section 9 (capability, principles, gap closed), gates 1 and 2 | C46: Required, portfolio | D46: Received
A47: Sponsor confirmation of the prioritization lens (email or minutes) (LENS) | B47: 01 Scoring Model weights, Governance record on the Read Me (who agreed the lens, and when) | C47: Required, portfolio | D47: Received
A48: Funding envelope or budget statement, or a written 'not yet defined' (FUNDING) | B48: 03 Sequencing (waves as approval tranches), Delivery confidence weighting | C48: Required, portfolio | D48: Received
A49: Current-state architecture or inventory of the affected systems (CURRENT_STATE) | B49: Dependencies, section 9 (gap closed), Risk reduction | C49: Recommended, portfolio | D49: Not provided
A50: Current run-cost baseline: cost export, invoices, licence list (COST_BASELINE) | B50: 06 Savings Case, KPI baselines, Cost optimization score | C50: Recommended, each initiative or portfolio | D50: Received
A51: Incident, risk and audit history (INCIDENTS) | B51: Risk reduction and Time criticality scores, 04 Risk Register | C51: Recommended, portfolio | D51: Received
A52: Security and compliance requirements, findings and review status (SECURITY) | B52: Security and compliance score, gates 3 and 8 | C52: Recommended, each initiative | D52: Received for all scored initiatives
A53: Ownership and support model: named people, RACI, org chart (OWNERSHIP) | B53: Sponsor, architecture owner, delivery owner, benefits owner, gate 4 | C53: Recommended, portfolio | D53: Not provided
A54: Resource and capacity plan: named roles and availability (CAPACITY) | B54: Capacity table on 03 Sequencing, Delivery confidence | C54: Recommended, portfolio | D54: Received
... A56: Earlier matrices, ADRs and forum decisions (PRIOR_DECISIONS) | B56: Consistency of scores, 07 Decision Log, gate 10 | C56: Optional, portfolio | D56: Not provided
A58: Document register
A59: Type and initiative | B59: Document and provider | C59: Version or date | D59: Status
A60: PROPOSAL / P1 | B60: Proposal P1 (Priya Narang) | D60: Received
A61: PROPOSAL / P2 | B61: Proposal P2 (Priya Narang) | D61: Received
A62: PROPOSAL / P3 | B62: Proposal P3 (Priya Narang) | D62: Received
A63: PROPOSAL / P4 | B63: Proposal P4 (Tomas Ellery) | D63: Received
A64: PROPOSAL / P5 | B64: Idea P5 (Joss Penhallow) | D64: Received
A65: ESTIMATE / P1 | B65: Estimate P1 (K. Dunmore) | D65: Received
A66: ESTIMATE / P2 | B66: Estimate P2 (K. Dunmore) | D66: Received
A67: ESTIMATE / P3 | B67: Estimate P3 (K. Dunmore) | D67: Received
A68: ESTIMATE / P4 | B68: Estimate P4 (deck total differs from line items) (L. Hartwell) | D68: Received
A69: ESTIMATE / P5 | B69: No estimate exists (Joss Penhallow) | D69: Not available
A70: TARGET_STATE / ALL | B70: Target-state architecture extract, v2 (R. Alder) | C70: 2025-11 | D70: Received
A71: LENS / ALL | B71: CFO email on prioritisation (Dana Whitcombe) | C71: 2026-03-02 | D71: Received
A72: FUNDING / ALL | B72: CFO memo: no approved budget, first tranche up to 150,000 (Dana Whitcombe) | C72: 2026-03-04 | D72: Received
A73: COST_BASELINE / P2 | B73: Finance export, file service (Finance) | C73: 2026-02 | D73: Received
A74: COST_BASELINE / P3 | B74: Finance export, monitoring tools (Finance) | C74: 2026-02 | D74: Received
A75: COST_BASELINE / P4 | B75: Order-management platform not in export (Finance) | D75: Requested
A76: INCIDENTS / ALL | B76: Incident and audit history Sep 2025 to Feb 2026 (Operations) | C76: 2026-02 | D76: Received
A77: SECURITY / ALL | B77: SEC-07 and review status (Marta Quesnel) | C77: 2026-03-05 | D77: Received
A78: CAPACITY / ALL | B78: Capacity April to October 2026 (Delivery lead) | D78: Received
A79: CONTRACTS / ALL | B79: Contract extract (Procurement) | D79: Received

Sheet 01 Scoring Model
A1: Scoring model
A2: Lens: run_cost. Changing a weight recalculates every project sheet and the summary.
A4: Weights
A5: Dimension | B5: Weight | C5: Rationale
A6: Business value | B6: 0.1 | C6: Business outcome, not just technical change.
A7: Cost optimization and savings | B7: 0.35 | C7: Highest weight: sponsor asked to reduce run cost first (LENS).
A8: Time criticality | B8: 0.15 | C8: Second priority per sponsor: deadline risk.
A9: Risk reduction and resilience | B9: 0.1 | C9: Reduction in incidents and single points of failure.
A10: Security and compliance | B10: 0.05 | C10: Net change in security posture. Can be negative.
A11: Delivery confidence | B11: 0.15 | C11: Capacity and clarity of scope.
A12: Strategic and architecture alignment | B12: 0.1 | C12: Fit to target-state principles.
A13: Total | B13: =SUM(B6:B12) -> 1 | C13: Must equal 100 percent.
A15: Lens presets
A16: Preset | B16: Business value | C16: Cost optimization and savings | D16: Time criticality | E16: Risk reduction and resilience | F16: Security and compliance | G16: Delivery confidence | H16: Strategic and architecture alignment
A17: balanced | B17: 0.2 | C17: 0.2 | D17: 0.2 | E17: 0.1 | F17: 0.1 | G17: 0.1 | H17: 0.1
A18: run_cost | B18: 0.1 | C18: 0.35 | D18: 0.15 | E18: 0.1 | F18: 0.05 | G18: 0.15 | H18: 0.1
A19: deadline_risk | B19: 0.1 | C19: 0.1 | D19: 0.35 | E19: 0.2 | F19: 0.05 | G19: 0.1 | H19: 0.1
A20: delivery_speed | B20: 0.15 | C20: 0.1 | D20: 0.15 | E20: 0.1 | F20: 0.05 | G20: 0.35 | H20: 0.1
A21: security | B21: 0.1 | C21: 0.1 | D21: 0.1 | E21: 0.2 | F21: 0.35 | G21: 0.05 | H21: 0.1
A23: Copy a preset row into B6:B12 to switch lens. Confirm the lens with the sponsor before scoring, not after.
A25: Score anchors, 1 to 5
A26: Dimension | C26: 1 | D26: 2 | E26: 3 | F26: 4 | G26: 5
A27: Business value | C27: No measurable business outcome; internal convenience only. | D27: Efficiency gain for one team, no quantified baseline. | E27: Quantified efficiency or quality gain for a defined process. | F27: Removes a live operational blind spot or unlocks decisions across teams. | G27: Direct revenue, contractual, or client-facing outcome.
A28: Cost optimization and savings | C28: No savings; adds run cost. | D28: Soft labour savings only, not booked. | E28: Modest run-cost reduction, single digit percent of the affected spend. | F28: Material and measurable reduction, or a direct enabler of one. | G28: Primary purpose is cost reduction with a named savings target.
A29: Time criticality | C29: No deadline. Can slip a year with no consequence. | D29: Preferable this year, no consequence if deferred. | E29: A live problem is costing time or risk every month it waits. | F29: Dependency window or vendor change makes deferral expensive. | G29: Hard external deadline or an already unsupported component.
A30: Risk reduction and resilience | C30: No change to risk posture. | D30: Marginal improvement. | E30: Reduces the frequency or blast radius of a known failure mode. | F30: Removes a recurring incident cause or restores a lost safety net. | G30: Removes a single point of failure with client-visible consequences.
A31: Security and compliance | C31: Increases attack surface with no offsetting control. | D31: Net neutral, or new surface offset by new controls. | E31: Minor control improvement. | F31: Removes standing credentials, adds auditability or least privilege. | G31: Closes an audit or regulatory finding.
A32: Delivery confidence | C32: Novel, undefined scope, unproven pattern, external dependency. | D32: Large scope with material unknowns. | E32: Well understood work with normal coordination overhead. | F32: Proven pattern already running elsewhere in the estate. | G32: Small, bounded, single team, reversible in hours.
A33: Strategic and architecture alignment | C33: Conflicts with target-state architecture. | D33: Tactical, creates no reusable asset. | E33: Consistent with standards, no reuse beyond itself. | F33: Advances a target-state standard reusable by other workloads. | G33: Establishes or completes an enterprise standard.

Sheet 02 Portfolio Summary
A1: Portfolio summary
A2: Everything pulls from the project sheets. Weights come from '01 Scoring Model'.
A4: Ranked portfolio
A5: ID | B5: Project | C5: Estimated cost (USD) | D5: Duration (months) | E5: Weighted score | F5: Rank | G5: Score per $100k | H5: Time criticality | I5: Delivery confidence | J5: Cost optimization | K5: Recommended wave
A6: P1 | B6: =IF('P1'!B6="","",'P1'!B6) -> Cloud cost visibility and tagging | C6: =IF('P1'!B10="","",'P1'!B10) -> 48000 | D6: =IF('P1'!B11="","",'P1'!B11) -> 2 | E6: ='P1'!$D$27 -> 3.45 | F6: =IF(E6="","",RANK(E6,$E$6:$E$10)) -> 2 | G6: =IFERROR(E6/(C6/100000),"") -> 7.1875 | H6: =IF('P1'!$B$22="","",'P1'!$B$22) -> 3 | I6: =IF('P1'!$B$25="","",'P1'!$B$25) -> 4 | J6: =IF('P1'!$B$21="","",'P1'!$B$21) -> 4 | K6: =IF('P1'!B14="","",'P1'!B14) -> Wave 1
A7: P2 | B7: =IF('P2'!B6="","",'P2'!B6) -> Retire the on-premises file servers | C7: =IF('P2'!B10="","",'P2'!B10) -> 96000 | D7: =IF('P2'!B11="","",'P2'!B11) -> 4 | E7: ='P2'!$D$27 -> 4.1 | F7: =IF(E7="","",RANK(E7,$E$6:$E$10)) -> 1 | G7: =IFERROR(E7/(C7/100000),"") -> 4.2708333 | H7: =IF('P2'!$B$22="","",'P2'!$B$22) -> 5 | I7: =IF('P2'!$B$25="","",'P2'!$B$25) -> 4 | J7: =IF('P2'!$B$21="","",'P2'!$B$21) -> 4 | K7: =IF('P2'!B14="","",'P2'!B14) -> Wave 1
A8: P3 | B8: =IF('P3'!B6="","",'P3'!B6) -> Consolidate three monitoring tools | C8: =IF('P3'!B10="","",'P3'!B10) -> 72000 | D8: =IF('P3'!B11="","",'P3'!B11) -> 3 | E8: ='P3'!$D$27 -> 3.25 | F8: =IF(E8="","",RANK(E8,$E$6:$E$10)) -> 3 | G8: =IFERROR(E8/(C8/100000),"") -> 4.5138889 | H8: =IF('P3'!$B$22="","",'P3'!$B$22) -> 4 | I8: =IF('P3'!$B$25="","",'P3'!$B$25) -> 3 | J8: =IF('P3'!$B$21="","",'P3'!$B$21) -> 3 | K8: =IF('P3'!B14="","",'P3'!B14) -> Wave 2
A9: P4 | B9: =IF('P4'!B6="","",'P4'!B6) -> Containerize order management on self-managed Kubernetes | C9: =IF('P4'!B10="","",'P4'!B10) -> 220000 | D9: =IF('P4'!B11="","",'P4'!B11) -> 5 | E9: ='P4'!$D$27 -> 1.95 | F9: =IF(E9="","",RANK(E9,$E$6:$E$10)) -> 4 | G9: =IFERROR(E9/(C9/100000),"") -> 0.88636364 | H9: =IF('P4'!$B$22="","",'P4'!$B$22) -> 2 | I9: =IF('P4'!$B$25="","",'P4'!$B$25) -> 2 | J9: =IF('P4'!$B$21="","",'P4'!$B$21) -> 2 | K9: =IF('P4'!B14="","",'P4'!B14) -> Hold
A10: P5 | B10: =IF('P5'!B6="","",'P5'!B6) -> Customer portal with an AI assistant | C10: =IF('P5'!B10="","",'P5'!B10) | D10: =IF('P5'!B11="","",'P5'!B11) | E10: ='P5'!$D$27 | F10: =IF(E10="","",RANK(E10,$E$6:$E$10)) | G10: =IFERROR(E10/(C10/100000),"") | H10: =IF('P5'!$B$22="","",'P5'!$B$22) | I10: =IF('P5'!$B$25="","",'P5'!$B$25) | J10: =IF('P5'!$B$21="","",'P5'!$B$21) | K10: =IF('P5'!B14="","",'P5'!B14) -> Hold
B11: Portfolio | C11: =SUM(C6:C10) -> 436000 | E11: =IFERROR(AVERAGE(E6:E10),"") -> 3.1875
A14: How to read this
A15: P2 ranks first on the run-cost lens: hard date, evidenced saving and the best case for a managed service. P1 has the best score per $100k and enables the others.
A16: P4 scores lowest and should stay on hold: it breaches SEC-07, needs more architect hours than exist and has no cost baseline.
A17: P5 is not scored. It has no business case or estimate.

Sheet 03 Sequencing
A1: Sequencing, dependencies and capacity
A2: Recommended delivery order and the constraints that shape it
A4: Recommended waves
A5: Wave | B5: Projects | C5: Indicative window | D5: Cost (USD) | E5: Why this grouping | F5: Entry condition
A6: Wave 1 | B6: P1, P2 | C6: April to July 2026 | D6: 144000 | E6: P2 has the hard date and the largest evidenced saving; P1 provides the baseline and is cheap. Together 144,000, inside the first tranche of 150,000. | F6: Board approval of the first tranche on 2026-03-24. Name the shared-service tag owner. Agree the warehouse cutover window.
A7: Wave 2 | B7: P3 | C7: August to October 2026 | D7: 72000 | E7: Needs P1 first so ingest can be attributed. Decision needed before the tool C notice date of 2026-09-16. | F7: Second tranche approved after the 2026-06-01 review. Ingest volume agreed.
A8: Wave 3
A9: Hold | B9: P4, P5 | C9: Not scheduled | D9: 0 | E9: P4: security breach of SEC-07, architect capacity impossible, no baseline. P5: no business case or estimate. | F9: P4: design that meets SEC-07, evidenced baseline, resequenced capacity. P5: a business case and an estimate.
B10: Total | D10: =SUM(D6:D9) -> 216000
A12: Cross-project dependencies
A13: From | B13: To | C13: Type | D13: Strength | E13: What it means for sequencing | F13: Owner
A14: P1 | B14: P3 | C14: Enables | D14: Strong | E14: P1 tags allow ingest cost to be attributed per team. | F14: Priya Narang
A15: P1 | B15: P4 | C15: Enables | D15: Strong | E15: P1 would supply the missing run-cost baseline for P4. | F15: Priya Narang
A16: P3 | B16: P4 | C16: Commercial | D16: Medium | E16: Cluster telemetry adds volume to the consumption-billed platform that P3 does not model. | F16: Priya Narang
A17: P2 | B17: P4 | C17: Capacity | D17: Strong | E17: R. Alder is needed in the same months by P2 (April to July) and P4 (June to October). | F17: Delivery lead
A18: P2 | B18: P3 | C18: Capacity | D18: Medium | E18: R. Alder has 120 hours in August to October for P3 only if P4 is not running. | F18: Delivery lead
A20: Resource contention
A21: Role | B21: Committed across the portfolio | C21: Peak concurrent demand | E21: Constraint
A22: Solutions Architect | B22: 1 | C22: 2 | E22: 160 productive hours a month, no backup. Named on every proposal. Demand: Apr-May P1 60 + P2 75 = 135; Jun-Jul P2 75 + P4 220 = 295; Aug-Oct P3 40 + P4 220 = 260.
A23: Infrastructure engineers | B23: 2 | E23: 150 hours each a month. P1 and P2 fit.
A24: Platform engineers | B24: 2 | E24: 100 hours each a month, shared with operations. P4 needs 900 hours each over 5 months.

Sheet 04 Risk Register
A1: Consolidated risk register
A2: All project risks, ranked by initial likelihood times impact
A4: Risks across the portfolio
A5: ID | B5: Project | C5: Risk | D5: Likelihood | E5: Impact | F5: Score | G5: Mitigation | H5: Owner | I5: Response | J5: Residual
A6: R01 | B6: P3 | C6: Ingest volume grows and the bill exceeds the estimate | D6: High | E6: High | F6: 9 | G6: Cap ingest per team, review monthly, set a budget alert. | H6: Priya Narang | I6: Mitigate | J6: 4
A7: R02 | B7: P4 | C7: Credentials stored as keys on nodes breach SEC-07 | D7: High | E7: High | F7: 9 | G7: Redesign to managed identity or drop the self-managed design. | H7: Marta Quesnel | I7: Avoid
A8: R03 | B8: P4 | C8: Architect capacity exceeded: 1,100 hours against 800 available | D8: High | E8: High | F8: 9 | G8: Resequence, split the scope or reduce architect hours before approval. | H8: Tomas Ellery | I8: Mitigate | J8: 4
A9: R04 | B9: P4 | C9: Unknown refactor scope inflates cost | D9: High | E9: High | F9: 9 | G9: Fixed-scope assessment before approval. | H9: L. Hartwell | I9: Mitigate | J9: 6
A10: R05 | B10: P2 | C10: Data loss or permission errors at cutover | D10: Medium | E10: Critical | F10: 8 | G10: Parallel run with reconciliation of permissions and file counts before the old shares are switched off. | H10: K. Dunmore | I10: Mitigate | J10: 3
A11: R06 | B11: P2 | C11: Warehouse cutover window too short | D11: High | E11: Medium | F11: 6 | G11: Agree the window with warehouse operations before scheduling. | H11: K. Dunmore | I11: Mitigate | J11: 4
A12: R07 | B12: P3 | C12: Alert migration gaps during the switch | D12: Medium | E12: High | F12: 6 | G12: Run old and new in parallel for one on-call cycle. | H12: K. Dunmore | I12: Mitigate | J12: 2
A13: R08 | B13: P4 | C13: Team has not run a production cluster | D13: High | E13: Medium | F13: 6 | G13: Managed Kubernetes service or training before approval. | H13: Tomas Ellery | I13: Mitigate | J13: 4
A14: R09 | B14: P1 | C14: Shared services have no tag owner, so spend stays unallocated | D14: Medium | E14: Medium | F14: 4 | G14: Name an owner per shared service before enforcement starts. | H14: Priya Narang | I14: Mitigate | J14: 1
A15: R10 | B15: P2 | C15: OS support lapses before the migration completes | D15: Low | E15: Critical | F15: 4 | G15: Four month plan ends July 2026, six months before the date. Escalate if cutover slips past October. | H15: Priya Narang | I15: Accept
A16: R11 | B16: P1 | C16: Owners ignore dashboards | D16: Medium | E16: Low | F16: 2 | G16: Monthly review in the infrastructure meeting. | H16: K. Dunmore | I16: Accept
A18: Score is likelihood times impact, each 1 to 4 (Low, Medium, High, Critical). Red at 9 or above, amber from 6. Every red risk needs a named owner and a review date before its project is approved. Response is Mitigate, Accept, Transfer or Avoid. Residual is the score once the mitigation is in place.

Sheet 05 Open Questions
A1: Open questions and information gaps
A2: What is still owed, and the decision each answer unblocks
A4: Blocking questions, in priority order
A5: ID | B5: Project | C5: Area | D5: Question | E5: Why it matters and what it unblocks | F5: Owner to answer | G5: Status
A6: Q01 | B6: P2 | C6: Business | D6: What is the acceptable cutover window for the warehouse shares? | E6: Needed before the cutover can be scheduled. | F6: Warehouse operations | G6: Open
A7: Q02 | B7: P2 | C7: Business | D7: How long must the old shares be retained after cutover? | E7: Affects decommission date and cost. | F7: Priya Narang | G7: Open
A8: Q03 | B8: P1 | C8: Ownership | D8: Who owns the tags for shared services? | E8: Enforcement cannot start without an owner. | F8: Priya Narang | G8: Open
A9: Q04 | B9: P3 | C9: Cost | D9: What ingest volume should be assumed? | E9: Run cost ranges from 5,500 to 9,000 a month. | F9: Priya Narang | G9: Open
A10: Q05 | B10: P3 | C10: Commercial | D10: Is 2026-09-16 the decision date for tool C? | E10: Missing it commits 12 months at 2,700 a month. | F10: Priya Narang | G10: Open
A11: Q06 | B11: P4 | C11: Cost | D11: What is the run cost baseline of the order-management platform? | E11: The 30% claim cannot be tested without it. | F11: Tomas Ellery | G11: Open
A12: Q07 | B12: P4 | C12: Cost | D12: Why does the deck total of 205,000 differ from the line items of 220,000? | E12: Cost used for scoring is 220,000. | F12: L. Hartwell | G12: Open
A13: Q08 | B13: P4 | C13: Security | D13: How will the design meet SEC-07 (managed identity, provider or automated patching)? | E13: Blocks any approval. | F13: Marta Quesnel | G13: Open
A14: Q09 | B14: P4 | C14: Capacity | D14: How can 1,100 architect hours fit in the period? | E14: R. Alder has 800 productive hours in the 5 months. | F14: Tomas Ellery | G14: Open
A15: Q10 | B15: P5 | C15: Business case | D15: What is the business case, cost, duration and risk? | E15: Nothing to score until these exist. | F15: Joss Penhallow | G15: Open
A16: Q11 | B16: ALL | C16: Funding | D16: Will a second tranche follow the first-quarter review? | E16: Wave 2 depends on it. Total envelope is not defined. | F16: Dana Whitcombe | G16: Open

Sheet 06 Savings Case
A1: Savings case and payback
A2: Yellow cells are the inputs still owed. Everything else calculates.
A4: Payback model
A5: ID | B5: Project | C5: Build cost (USD) | D5: Current annual run cost (USD) | E5: Expected annual saving (USD) | F5: Saving % | G5: Payback (months) | H5: Evidence position
A6: P1 | B6: =IF('P1'!B6="","",'P1'!B6) -> Cloud cost visibility and tagging | C6: ='P1'!B10 -> 48000 | D6: 0 | E6: 0 | F6: =IFERROR(E6/D6,"") | G6: =IFERROR(C6/(E6/12),"Awaiting baseline") -> Awaiting baseline
A7: P2 | B7: =IF('P2'!B6="","",'P2'!B6) -> Retire the on-premises file servers | C7: ='P2'!B10 -> 96000 | D7: 112800 | E7: 66000 | F7: =IFERROR(E7/D7,"") -> 0.58510638 | G7: =IFERROR(C7/(E7/12),"Awaiting baseline") -> 17.454545 | H7: Current 9,400 a month falls to 3,900. 5,500 x 12 = 66,000.
A8: P3 | B8: =IF('P3'!B6="","",'P3'!B6) -> Consolidate three monitoring tools | C8: ='P3'!B10 -> 72000 | D8: 120000 | E8: 12000 | F8: =IFERROR(E8/D8,"") -> 0.1 | G8: =IFERROR(C8/(E8/12),"Awaiting baseline") -> 72 | H8: Conservative end of 1,000 to 4,500 a month. The vendor's 45% claim is not used.
A9: P4 | B9: =IF('P4'!B6="","",'P4'!B6) -> Containerize order management on self-managed Kubernetes | C9: ='P4'!B10 -> 220000 | D9: 0 | E9: 0 | F9: =IFERROR(E9/D9,"") | G9: =IFERROR(C9/(E9/12),"Awaiting baseline") -> Awaiting baseline | H9: No baseline. No saving is claimed.
A10: P5 | B10: =IF('P5'!B6="","",'P5'!B6) -> Customer portal with an AI assistant | C10: ='P5'!B10 -> 0 | D10: 0 | E10: 0 | F10: =IFERROR(E10/D10,"") | G10: =IFERROR(C10/(E10/12),"Awaiting baseline") -> Awaiting baseline
B11: Portfolio | C11: =SUM(C6:C10) -> 436000 | D11: =SUM(D6:D10) -> 232800 | E11: =SUM(E6:E10) -> 78000 | F11: =IFERROR(E11/D11,"") -> 0.33505155 | G11: =IFERROR(C11/(E11/12),"Awaiting baseline") -> 67.076923
A13: Columns D and E are the only inputs. An initiative that is a pure enabler should show zero expected saving and be argued on the grounds that it makes the other rows provable.

Sheet 07 Decision Log
A1: Decision log
A2: What the forum decided, on what conditions, and who answers for it
A4: Decisions
A5: Ref | B5: Project | C5: Decision | D5: Conditions and rationale | E5: Decided by (named) | F5: Date | G5: Reference (ADR or minutes)
A6: D01 | B6: P1 | C6: Approved with conditions | D6: Name the shared-service tag owner before enforcement. Subject to board approval of the first tranche on 2026-03-24. | E6: Dana Whitcombe | F6: 2026-03-09 | G6: TEST SCENARIO recommendation, not a real decision
A7: D02 | B7: P2 | C7: Approved with conditions | D7: Agree warehouse cutover window and retention period before cutover is scheduled. | E7: Dana Whitcombe | F7: 2026-03-09 | G7: TEST SCENARIO recommendation, not a real decision
A8: D03 | B8: P3 | C8: Deferred | D8: Decide after the 2026-06-01 review and before the 2026-09-16 notice date; agree ingest volume. | E8: Dana Whitcombe | F8: 2026-03-09 | G8: TEST SCENARIO recommendation, not a real decision
A9: D04 | B9: P4 | C9: Held | D9: Requires a design that meets SEC-07, an evidenced cost baseline and a resourcing plan. | E9: Dana Whitcombe | F9: 2026-03-09 | G9: TEST SCENARIO recommendation, not a real decision
A10: D05 | B10: P5 | C10: Held | D10: No business case or estimate. | E10: Dana Whitcombe | F10: 2026-03-09 | G10: TEST SCENARIO recommendation, not a real decision
A12: Decisions: Approved, Approved with conditions, Deferred, Held, Rejected. A deferred or held initiative states what would change the decision. The scores recommend; this sheet records what was decided.

Sheet P1
A1: P1. Cloud cost visibility and tagging
A2: Enterprise Architecture Impact Matrix
A4: 1. Project profile
A5: Project ID | B5: P1
A6: Project name | B6: Cloud cost visibility and tagging | E6: Pulled by '02 Portfolio Summary'. Keep it in this cell.
A7: Business sponsor | B7: Priya Narang, Head of Infrastructure | E7: Named individual required before EA approval.
A8: Architecture owner | B8: R. Alder, Solutions Architect | E8: Named individual required before EA approval.
A9: Delivery owner | B9: K. Dunmore, Delivery Lead | E9: Named individual required before EA approval.
A10: Estimated cost (USD) | B10: 48000 | E10: ESTIMATE-P1. Line items sum to 48,000.
A11: Estimated duration (months) | B11: 2 | E11: 2 months, April to May 2026. R. Alder 120 hours.
A12: Hard external deadline | B12: None. It is an enabler for P2, P3 and P4 savings claims.
A13: Current status | B13: Proposed, awaiting first tranche
A14: Recommended wave | B14: Wave 1 | E14: See '03 Sequencing'.
A15: Basis of estimate | B15: PROPOSAL-P1, ESTIMATE-P1, TARGET_STATE principle 2. | E15: Cite the document and slide or section.
A17: 2. Weighted impact assessment
A18: Enter 1 to 5 in column B. Anchors are on '01 Scoring Model'. Column C is a link; do not edit it.
A19: Dimension | B19: Score (1-5) | C19: Weight | D19: Weighted | E19: Assessment | F19: Owner | G19: Evidence and basis
A20: Business value | B20: 3 | C20: ='01 Scoring Model'!$B$6 -> 0.1 | D20: =IF(B20="","",B20*C20) -> 0.3 | E20: Allocation of spend to a named owner moves from about 60% to 100%. It supports decisions but does not itself change the business outcome. | F20: Priya Narang | G20: PROPOSAL-P1 benefits.
A21: Cost optimization and savings | B21: 4 | C21: ='01 Scoring Model'!$B$7 -> 0.35 | D21: =IF(B21="","",B21*C21) -> 1.4 | E21: No saving of its own, but it is the baseline that lets other savings be evidenced and booked. High value as an enabler. | F21: Finance | G21: PROPOSAL-P1; COST_BASELINE shows P4 has no baseline.
A22: Time criticality | B22: 3 | C22: ='01 Scoring Model'!$B$8 -> 0.15 | D22: =IF(B22="","",B22*C22) -> 0.45 | E22: No deadline and nothing gets worse monthly if it waits, but P2 and P3 savings cannot be proven until it lands. | F22: Priya Narang | G22: PROPOSAL-P1; ESTIMATE-P1.
A23: Risk reduction and resilience | B23: 2 | C23: ='01 Scoring Model'!$B$9 -> 0.1 | D23: =IF(B23="","",B23*C23) -> 0.2 | E23: Little risk reduction. Untagged spend is a control weakness, not an incident source. | F23: Priya Narang | G23: INCIDENTS shows no cost-allocation incident.
A24: Security and compliance | B24: 2 | C24: ='01 Scoring Model'!$B$10 -> 0.05 | D24: =IF(B24="","",B24*C24) -> 0.1 | E24: Neutral to slightly positive. Security review marked not required. | F24: Marta Quesnel | G24: SECURITY review status.
A25: Delivery confidence | B25: 4 | C25: ='01 Scoring Model'!$B$11 -> 0.15 | D25: =IF(B25="","",B25*C25) -> 0.6 | E25: Small, well understood scope, two months, effort fits capacity. | F25: R. Alder | G25: ESTIMATE-P1; CAPACITY.
A26: Strategic and architecture alignment | B26: 4 | C26: ='01 Scoring Model'!$B$12 -> 0.1 | D26: =IF(B26="","",B26*C26) -> 0.4 | E26: Implements target-state principle 2 directly. | F26: R. Alder | G26: TARGET_STATE principle 2.
A27: Weighted priority score | D27: =IF(COUNT(B20:B26)=0,"",ROUND(SUM(D20:D26),2)) -> 3.45 | E27: Out of 5.00. Compare on '02 Portfolio Summary'.
A29: 3. Scope
A30: In scope | E30: Explicitly out of scope
A31: Tagging policy and enforcement | E31: Cost reduction work
A32: Cost export pipeline | E32: Chargeback to business units
A33: Owner dashboards
A34: Owner training
A36: 4. Dependencies
A37: Type | B37: Depends on | E37: Nature of the dependency | F37: Owner | G37: Criticality
A38: Internal | B38: Ownership of shared-service tags | E38: Shared services have no obvious owner. Needs a decision before enforcement. | F38: Priya Narang | G38: High
A39: Resource | B39: Solutions Architect capacity | E39: 120 hours in April and May. Check against P2 in the same months. | F39: Delivery lead | G39: Medium
A41: 5. Key risks
A42: Risk | B42: Likelihood | C42: Impact | D42: Score | E42: Mitigation | F42: Owner | G42: Response (residual score)
A43: Shared services have no tag owner, so spend stays unallocated | B43: Medium | C43: Medium | D43: 4 | E43: Name an owner per shared service before enforcement starts. | F43: Priya Narang | G43: Mitigate (residual 1)
A44: Owners ignore dashboards | B44: Medium | C44: Low | D44: 2 | E44: Monthly review in the infrastructure meeting. | F44: K. Dunmore | G44: Accept
A45: Likelihood times impact, each 1 to 4 (Low, Medium, High, Critical). Red at 9 or above: needs a named owner and a review date. Optional 6th to 8th items per risk: response, residual likelihood, residual impact.
A47: 6. Success KPIs
A48: KPI | B48: Baseline | D48: Target | E48: Measurement source | F48: Measured by
A49: Share of cloud spend allocated to a named owner | B49: About 60% | D49: 100% | E49: Monthly cost export | F49: 60 days after delivery
A50: Unowned shared-service spend | B50: Not measured | D50: Zero | E50: Monthly cost export | F50: 60 days after delivery
A52: 7. EA governance gates
A53: Gate | B53: Status | E53: Evidence or artefact | F53: Reviewer | G53: Date cleared
A54: Alignment with a named business capability | B54: Met | E54: TARGET_STATE principle 2 | F54: R. Alder
A55: Architecture standards compliance | B55: Met | E55: Uses native tagging and cost export | F55: R. Alder
A56: Security review completed | B56: Not started | E56: Security review not required per SECURITY | F56: Marta Quesnel
A57: Operational ownership defined (named team, not a role) | B57: Partial | E57: Delivery lead named, run owner for dashboards not named | F57: Priya Narang
A58: Success KPIs agreed with a measured baseline | B58: Partial | E58: Allocation baseline of about 60% stated, source not provided | F58: Finance
A59: Rollback strategy documented and tested | B59: Not applicable | E59: No production change to roll back | F59: R. Alder
A60: Cost model and payback agreed with FinOps | B60: Met | E60: Cost and run cost in ESTIMATE-P1 | F60: Finance
A61: Data, retention and privacy position cleared | B61: Not applicable | E61: No personal data | F61: R. Alder
A62: Change and CAB approval path confirmed | B62: Not started | E62: Change path not confirmed | F62: PMO
A63: Architecture decision recorded and traceable (ADR or decision log) | B63: Not started | E63: ADR not drafted | F63: R. Alder
A64: Valid statuses: Met, Partial, Not started, Not met, Not applicable.
A66: 8. Open questions
A67: Q1 | B67: Who owns the tags for shared services?
A68: Q2 | B68: What is the source of the 60% allocation figure?
A70: 9. Traceability and benefits
A71: Business capability or value stream | B71: Financial management of cloud | E71: Name the capability this changes. Gate 1 depends on it.
A72: Architecture principles addressed | B72: 2 Every cloud cost has a named owner | E72: Optional. The principles this initiative follows or tests.
A73: Gap closed (baseline to target) | B73: Baseline: about 60% of spend allocated. Target: 100%. | E73: One line: where it is today, where it ends up.
A74: Benefits owner (named) | B74: Priya Narang, Head of Infrastructure | E74: The person who answers for the benefit after delivery.
A75: Benefits review date | B75: 90 days after delivery | E75: When the KPIs above are checked against the business case.
A76: Standards references | B76: TOGAF Phase E/F work package; COBIT APO06 | E76: Optional. TOGAF phase or artefact, COBIT objective IDs.

Sheet P2
A1: P2. Retire the on-premises file servers
A2: Enterprise Architecture Impact Matrix
A4: 1. Project profile
A5: Project ID | B5: P2
A6: Project name | B6: Retire the on-premises file servers | E6: Pulled by '02 Portfolio Summary'. Keep it in this cell.
A7: Business sponsor | B7: Priya Narang, Head of Infrastructure | E7: Named individual required before EA approval.
A8: Architecture owner | B8: R. Alder, Solutions Architect | E8: Named individual required before EA approval.
A9: Delivery owner | B9: K. Dunmore, Delivery Lead | E9: Named individual required before EA approval.
A10: Estimated cost (USD) | B10: 96000 | E10: ESTIMATE-P2. Line items sum to 96,000.
A11: Estimated duration (months) | B11: 4 | E11: 4 months, April to July 2026. R. Alder 300 hours.
A12: Hard external deadline | B12: 2027-01-31: Windows Server 2012 R2 extended support ends; insurer requires remediation by that date.
A13: Current status | B13: Proposed, awaiting first tranche
A14: Recommended wave | B14: Wave 1 | E14: See '03 Sequencing'.
A15: Basis of estimate | B15: PROPOSAL-P2, ESTIMATE-P2, COST_BASELINE, INCIDENTS, CONTRACTS, SECURITY. | E15: Cite the document and slide or section.
A17: 2. Weighted impact assessment
A18: Enter 1 to 5 in column B. Anchors are on '01 Scoring Model'. Column C is a link; do not edit it.
A19: Dimension | B19: Score (1-5) | C19: Weight | D19: Weighted | E19: Assessment | F19: Owner | G19: Evidence and basis
A20: Business value | B20: 3 | C20: ='01 Scoring Model'!$B$6 -> 0.1 | D20: =IF(B20="","",B20*C20) -> 0.3 | E20: Removes recurring outages and an audit finding. The business outcome is reliability and compliance rather than new capability. | F20: Priya Narang | G20: INCIDENTS: 3 unplanned outages in 6 months.
A21: Cost optimization and savings | B21: 4 | C21: ='01 Scoring Model'!$B$7 -> 0.35 | D21: =IF(B21="","",B21*C21) -> 1.4 | E21: Run cost 9,400 a month falls to 3,900 a month: 5,500 a month, about 66,000 a year, backed by the finance export. | F21: Finance | G21: COST_BASELINE (9,400); ESTIMATE-P2 (3,900).
A22: Time criticality | B22: 5 | C22: ='01 Scoring Model'!$B$8 -> 0.15 | D22: =IF(B22="","",B22*C22) -> 0.75 | E22: Hard external date: OS support ends 2027-01-31 and the insurer requires remediation by then. Four months of work leaves margin. | F22: Priya Narang | G22: CONTRACTS; INCIDENTS open audit finding.
A23: Risk reduction and resilience | B23: 4 | C23: ='01 Scoring Model'!$B$9 -> 0.1 | D23: =IF(B23="","",B23*C23) -> 0.4 | E23: Removes the failing disk array behind three outages and closes the unsupported-OS audit finding. | F23: Priya Narang | G23: INCIDENTS.
A24: Security and compliance | B24: 5 | C24: ='01 Scoring Model'!$B$10 -> 0.05 | D24: =IF(B24="","",B24*C24) -> 0.25 | E24: Closes an open audit finding. Security review done with no objections. | F24: Marta Quesnel | G24: SECURITY review status; INCIDENTS audit finding.
A25: Delivery confidence | B25: 4 | C25: ='01 Scoring Model'!$B$11 -> 0.15 | D25: =IF(B25="","",B25*C25) -> 0.6 | E25: Pilot on the finance share ran four weeks with no issues. Cutover window for warehouse shares is still open. | F25: K. Dunmore | G25: PROPOSAL-P2 summary.
A26: Strategic and architecture alignment | B26: 4 | C26: ='01 Scoring Model'!$B$12 -> 0.1 | D26: =IF(B26="","",B26*C26) -> 0.4 | E26: Retires on-premises hardware, matching the target-state direction and principle 1. | F26: R. Alder | G26: TARGET_STATE principles 1 and 5.
A27: Weighted priority score | D27: =IF(COUNT(B20:B26)=0,"",ROUND(SUM(D20:D26),2)) -> 4.1 | E27: Out of 5.00. Compare on '02 Portfolio Summary'.
A29: 3. Scope
A30: In scope | E30: Explicitly out of scope
A31: Data migration | E31: Document management system
A32: Permission mapping | E32: Desktop client changes
A33: Parallel run
A34: Cutover
A35: Decommission
A37: 4. Dependencies
A38: Type | B38: Depends on | E38: Nature of the dependency | F38: Owner | G38: Criticality
A39: Internal | B39: P1 Cost visibility | E39: P1 gives the baseline against which the saving is shown. P2 can proceed without it but the saving is then asserted by finance export only. | F39: Priya Narang | G39: Medium
A40: Resource | B40: Solutions Architect capacity | E40: 300 hours across April to July, 75 a month. | F40: Delivery lead | G40: Medium
A41: Business | B41: Warehouse cutover window | E41: Not agreed. Needed before cutover is scheduled. | F41: Warehouse operations | G41: High
A43: 5. Key risks
A44: Risk | B44: Likelihood | C44: Impact | D44: Score | E44: Mitigation | F44: Owner | G44: Response (residual score)
A45: Data loss or permission errors at cutover | B45: Medium | C45: Critical | D45: 8 | E45: Parallel run with reconciliation of permissions and file counts before the old shares are switched off. | F45: K. Dunmore | G45: Mitigate (residual 3)
A46: Warehouse cutover window too short | B46: High | C46: Medium | D46: 6 | E46: Agree the window with warehouse operations before scheduling. | F46: K. Dunmore | G46: Mitigate (residual 4)
A47: OS support lapses before the migration completes | B47: Low | C47: Critical | D47: 4 | E47: Four month plan ends July 2026, six months before the date. Escalate if cutover slips past October. | F47: Priya Narang | G47: Accept
A48: Likelihood times impact, each 1 to 4 (Low, Medium, High, Critical). Red at 9 or above: needs a named owner and a review date. Optional 6th to 8th items per risk: response, residual likelihood, residual impact.
A50: 6. Success KPIs
A51: KPI | B51: Baseline | D51: Target | E51: Measurement source | F51: Measured by
A52: Unplanned file-service outage hours per 6 months | B52: 19 hours (3 outages) | D52: 0 | E52: Incident records | F52: 90 days after cutover
A53: File service run cost per month | B53: 9,400 | D53: 3,900 | E53: Finance cost export | F53: 60 days after decommission
A54: Open audit finding on unsupported OS | B54: Open | D54: Closed | E54: Audit register | F54: Before 2027-01-31
A56: 7. EA governance gates
A57: Gate | B57: Status | E57: Evidence or artefact | F57: Reviewer | G57: Date cleared
A58: Alignment with a named business capability | B58: Met | E58: Enterprise file and content services | F58: R. Alder
A59: Architecture standards compliance | B59: Met | E59: Managed service per principle 1 | F59: R. Alder
A60: Security review completed | B60: Met | E60: Review done, no objections | F60: Marta Quesnel
A61: Operational ownership defined (named team, not a role) | B61: Partial | E61: Delivery lead named, run owner after handover not named | F61: Priya Narang
A62: Success KPIs agreed with a measured baseline | B62: Met | E62: Outage hours and run cost baselines in INCIDENTS and COST_BASELINE | F62: Finance
A63: Rollback strategy documented and tested | B63: Partial | E63: Old shares retained after cutover, retention period not agreed | F63: K. Dunmore
A64: Cost model and payback agreed with FinOps | B64: Met | E64: Cost, run cost and saving agreed with finance export | F64: Finance
A65: Data, retention and privacy position cleared | B65: Partial | E65: Permission mapping covers access, retention of file data not confirmed | F65: R. Alder
A66: Change and CAB approval path confirmed | B66: Not started | E66: Cutover change window not agreed | F66: PMO
A67: Architecture decision recorded and traceable (ADR or decision log) | B67: Not started | E67: ADR not drafted | F67: R. Alder
A68: Valid statuses: Met, Partial, Not started, Not met, Not applicable.
A70: 8. Open questions
A71: Q1 | B71: What is the acceptable cutover window for the warehouse shares?
A72: Q2 | B72: How long must old shares be retained after cutover?
A74: 9. Traceability and benefits
A75: Business capability or value stream | B75: Enterprise file and content services | E75: Name the capability this changes. Gate 1 depends on it.
A76: Architecture principles addressed | B76: 1 Prefer managed services; 5 Close audit findings first | E76: Optional. The principles this initiative follows or tests.
A77: Gap closed (baseline to target) | B77: Baseline: six on-premises servers on an unsupported OS. Target: managed storage, hardware retired. | E77: One line: where it is today, where it ends up.
A78: Benefits owner (named) | B78: Priya Narang, Head of Infrastructure | E78: The person who answers for the benefit after delivery.
A79: Benefits review date | B79: 90 days after decommission | E79: When the KPIs above are checked against the business case.
A80: Standards references | B80: TOGAF Phase E/F work package; COBIT APO12, BAI02 | E80: Optional. TOGAF phase or artefact, COBIT objective IDs.

Sheet P3
A1: P3. Consolidate three monitoring tools
A2: Enterprise Architecture Impact Matrix
A4: 1. Project profile
A5: Project ID | B5: P3
A6: Project name | B6: Consolidate three monitoring tools | E6: Pulled by '02 Portfolio Summary'. Keep it in this cell.
A7: Business sponsor | B7: Priya Narang, Head of Infrastructure | E7: Named individual required before EA approval.
A8: Architecture owner | B8: R. Alder, Solutions Architect | E8: Named individual required before EA approval.
A9: Delivery owner | B9: K. Dunmore, Delivery Lead | E9: Named individual required before EA approval.
A10: Estimated cost (USD) | B10: 72000 | E10: ESTIMATE-P3. Line items sum to 72,000. Run cost after delivery varies with ingest.
A11: Estimated duration (months) | B11: 3 | E11: 3 months, August to October 2026. R. Alder 120 hours.
A12: Hard external deadline | B12: 2026-09-16: notice date for tool C, which renews 2026-12-15 for 12 months at 2,700 a month.
A13: Current status | B13: Proposed, awaiting second tranche
A14: Recommended wave | B14: Wave 2 | E14: See '03 Sequencing'.
A15: Basis of estimate | B15: PROPOSAL-P3, ESTIMATE-P3, COST_BASELINE, INCIDENTS, CONTRACTS. | E15: Cite the document and slide or section.
A17: 2. Weighted impact assessment
A18: Enter 1 to 5 in column B. Anchors are on '01 Scoring Model'. Column C is a link; do not edit it.
A19: Dimension | B19: Score (1-5) | C19: Weight | D19: Weighted | E19: Assessment | F19: Owner | G19: Evidence and basis
A20: Business value | B20: 3 | C20: ='01 Scoring Model'!$B$6 -> 0.1 | D20: =IF(B20="","",B20*C20) -> 0.3 | E20: One alerting path replaces three. Two missed alerts in six months show the cost of splitting them. | F20: Priya Narang | G20: INCIDENTS: two delayed responses.
A21: Cost optimization and savings | B21: 3 | C21: ='01 Scoring Model'!$B$7 -> 0.35 | D21: =IF(B21="","",B21*C21) -> 1.05 | E21: Current spend 10,000 a month. After delivery 5,500 to 9,000 a month depending on ingest, so the saving is 1,000 to 4,500 a month, 12,000 to 54,000 a year. The vendor's 45% is the top of a range and is not used. Consumption billing and volume from P1 and P4 are not in the estimate. | F21: Finance | G21: COST_BASELINE; ESTIMATE-P3; PROPOSAL-P3.
A22: Time criticality | B22: 4 | C22: ='01 Scoring Model'!$B$8 -> 0.15 | D22: =IF(B22="","",B22*C22) -> 0.6 | E22: Soft deadline: notice for tool C is due 2026-09-16 and the project ends in October, so renewal is likely unless the decision is made earlier. | F22: Priya Narang | G22: CONTRACTS.
A23: Risk reduction and resilience | B23: 3 | C23: ='01 Scoring Model'!$B$9 -> 0.1 | D23: =IF(B23="","",B23*C23) -> 0.3 | E23: Fixes the missed-alert pattern but not the root cause of outages. | F23: K. Dunmore | G23: INCIDENTS.
A24: Security and compliance | B24: 3 | C24: ='01 Scoring Model'!$B$10 -> 0.05 | D24: =IF(B24="","",B24*C24) -> 0.15 | E24: Neutral. Security review not started. | F24: Marta Quesnel | G24: SECURITY review status.
A25: Delivery confidence | B25: 3 | C25: ='01 Scoring Model'!$B$11 -> 0.15 | D25: =IF(B25="","",B25*C25) -> 0.45 | E25: Moderate: new platform and billing model, R. Alder committed in the same months as P4 if P4 proceeds. | F25: R. Alder | G25: ESTIMATE-P3; CAPACITY.
A26: Strategic and architecture alignment | B26: 4 | C26: ='01 Scoring Model'!$B$12 -> 0.1 | D26: =IF(B26="","",B26*C26) -> 0.4 | E26: Implements target-state principle 3 and one observability platform. | F26: R. Alder | G26: TARGET_STATE principle 3.
A27: Weighted priority score | D27: =IF(COUNT(B20:B26)=0,"",ROUND(SUM(D20:D26),2)) -> 3.25 | E27: Out of 5.00. Compare on '02 Portfolio Summary'.
A29: 3. Scope
A30: In scope | E30: Explicitly out of scope
A31: Platform onboarding | E31: Application performance tracing
A32: Agent rollout | E32: Log retention redesign
A33: Alert migration
A34: Training
A36: 4. Dependencies
A37: Type | B37: Depends on | E37: Nature of the dependency | F37: Owner | G37: Criticality
A38: Internal | B38: P1 Cost visibility | E38: Ingest cost per team cannot be controlled without tagging. | F38: Priya Narang | G38: High
A39: Commercial | B39: Tool C renewal | E39: Notice due 2026-09-16 for the 2026-12-15 renewal. | F39: Priya Narang | G39: High
A40: Resource | B40: Solutions Architect capacity | E40: 120 hours in August to October. | F40: Delivery lead | G40: Medium
A42: 5. Key risks
A43: Risk | B43: Likelihood | C43: Impact | D43: Score | E43: Mitigation | F43: Owner | G43: Response (residual score)
A44: Ingest volume grows and the bill exceeds the estimate | B44: High | C44: High | D44: 9 | E44: Cap ingest per team, review monthly, set a budget alert. | F44: Priya Narang | G44: Mitigate (residual 4)
A45: Alert migration gaps during the switch | B45: Medium | C45: High | D45: 6 | E45: Run old and new in parallel for one on-call cycle. | F45: K. Dunmore | G45: Mitigate (residual 2)
A46: Likelihood times impact, each 1 to 4 (Low, Medium, High, Critical). Red at 9 or above: needs a named owner and a review date. Optional 6th to 8th items per risk: response, residual likelihood, residual impact.
A48: 6. Success KPIs
A49: KPI | B49: Baseline | D49: Target | E49: Measurement source | F49: Measured by
A50: Missed or one-tool-only alerts per 6 months | B50: 2 incidents | D50: 0 | E50: Incident records | F50: 90 days after cutover
A51: Monitoring tooling cost per month | B51: 10,000 | D51: Under 9,000 | E51: Finance cost export | F51: 60 days after cutover
A52: Ingest volume assumed | B52: TBC | D52: Agreed figure | E52: Platform vendor trial | F52: Before approval
A54: 7. EA governance gates
A55: Gate | B55: Status | E55: Evidence or artefact | F55: Reviewer | G55: Date cleared
A56: Alignment with a named business capability | B56: Met | E56: Observability and operations | F56: R. Alder
A57: Architecture standards compliance | B57: Met | E57: One platform per principle 3 | F57: R. Alder
A58: Security review completed | B58: Not started | E58: Security review not started | F58: Marta Quesnel
A59: Operational ownership defined (named team, not a role) | B59: Partial | E59: Run owner after handover not named | F59: Priya Narang
A60: Success KPIs agreed with a measured baseline | B60: Partial | E60: Spend baseline known, ingest volume baseline not | F60: Finance
A61: Rollback strategy documented and tested | B61: Partial | E61: Old tools kept until parallel run passes | F61: K. Dunmore
A62: Cost model and payback agreed with FinOps | B62: Partial | E62: Range of saving, not a point value; ingest not modelled | F62: Finance
A63: Data, retention and privacy position cleared | B63: Not started | E63: Data content of telemetry not classified | F63: Marta Quesnel
A64: Change and CAB approval path confirmed | B64: Not started | E64: Change path not confirmed | F64: PMO
A65: Architecture decision recorded and traceable (ADR or decision log) | B65: Not started | E65: ADR not drafted | F65: R. Alder
A66: Valid statuses: Met, Partial, Not started, Not met, Not applicable.
A68: 8. Open questions
A69: Q1 | B69: What ingest volume should be assumed?
A70: Q2 | B70: Is 2026-09-16 the decision date for tool C?
A72: 9. Traceability and benefits
A73: Business capability or value stream | B73: Observability and operations | E73: Name the capability this changes. Gate 1 depends on it.
A74: Architecture principles addressed | B74: 3 One observability platform | E74: Optional. The principles this initiative follows or tests.
A75: Gap closed (baseline to target) | B75: Baseline: three tools, 10,000 a month. Target: one platform, 5,500 to 9,000 a month. | E75: One line: where it is today, where it ends up.
A76: Benefits owner (named) | B76: Priya Narang, Head of Infrastructure | E76: The person who answers for the benefit after delivery.
A77: Benefits review date | B77: 90 days after cutover | E77: When the KPIs above are checked against the business case.
A78: Standards references | B78: TOGAF Phase E/F work package; COBIT APO05, BAI04 | E78: Optional. TOGAF phase or artefact, COBIT objective IDs.

Sheet P4
A1: P4. Containerize order management on self-managed Kubernetes
A2: Enterprise Architecture Impact Matrix
A4: 1. Project profile
A5: Project ID | B5: P4
A6: Project name | B6: Containerize order management on self-managed Kubernetes | E6: Pulled by '02 Portfolio Summary'. Keep it in this cell.
A7: Business sponsor | B7: Tomas Ellery, Head of Applications | E7: Named individual required before EA approval.
A8: Architecture owner | B8: R. Alder, Solutions Architect | E8: Named individual required before EA approval.
A9: Delivery owner | B9: L. Hartwell, Delivery Lead | E9: Named individual required before EA approval.
A10: Estimated cost (USD) | B10: 220000 | E10: ESTIMATE-P4 line items sum to 220,000. The proposal deck states 205,000, a 15,000 difference. 220,000 used.
A11: Estimated duration (months) | B11: 5 | E11: 5 months, June to October 2026. R. Alder 1,100 hours.
A12: Hard external deadline | B12: None stated.
A13: Current status | B13: Proposed, not recommended in current form
A14: Recommended wave | B14: Hold | E14: See '03 Sequencing'.
A15: Basis of estimate | B15: PROPOSAL-P4, ESTIMATE-P4, TARGET_STATE, SECURITY, CAPACITY, COST_BASELINE. | E15: Cite the document and slide or section.
A17: 2. Weighted impact assessment
A18: Enter 1 to 5 in column B. Anchors are on '01 Scoring Model'. Column C is a link; do not edit it.
A19: Dimension | B19: Score (1-5) | C19: Weight | D19: Weighted | E19: Assessment | F19: Owner | G19: Evidence and basis
A20: Business value | B20: 3 | C20: ='01 Scoring Model'!$B$6 -> 0.1 | D20: =IF(B20="","",B20*C20) -> 0.3 | E20: Release lead time 14 to 5 days is a real benefit but unevidenced. The 14-day figure has no source. One rollback in the last six months. | F20: Tomas Ellery | G20: PROPOSAL-P4; INCIDENTS (one rollback).
A21: Cost optimization and savings | B21: 2 | C21: ='01 Scoring Model'!$B$7 -> 0.35 | D21: =IF(B21="","",B21*C21) -> 0.7 | E21: The claimed 30% run cost reduction has no baseline: the order-management platform is not in the finance export and ESTIMATE-P4 states no run cost. No saving can be claimed. | F21: Finance | G21: COST_BASELINE note; ESTIMATE-P4.
A22: Time criticality | B22: 2 | C22: ='01 Scoring Model'!$B$8 -> 0.15 | D22: =IF(B22="","",B22*C22) -> 0.3 | E22: No deadline. | F22: Tomas Ellery | G22: PROPOSAL-P4.
A23: Risk reduction and resilience | B23: 2 | C23: ='01 Scoring Model'!$B$9 -> 0.1 | D23: =IF(B23="","",B23*C23) -> 0.2 | E23: Self-managed nodes add patching and cluster failure exposure. No incident history to remove. | F23: R. Alder | G23: PROPOSAL-P4 design notes.
A24: Security and compliance | B24: 1 | C24: ='01 Scoring Model'!$B$10 -> 0.05 | D24: =IF(B24="","",B24*C24) -> 0.05 | E24: Keys stored on nodes break SEC-07 and the managed-identity principle. Node patching moves from the provider to the platform team. Security review not started. Scored 1 until a design that meets SEC-07 exists. | F24: Marta Quesnel | G24: SECURITY SEC-07; PROPOSAL-P4 design notes.
A25: Delivery confidence | B25: 2 | C25: ='01 Scoring Model'!$B$11 -> 0.15 | D25: =IF(B25="","",B25*C25) -> 0.3 | E25: R. Alder is estimated at 1,100 hours over 5 months against 160 productive hours a month (800 available), and the team has not run a production cluster. | F25: R. Alder | G25: ESTIMATE-P4; CAPACITY; PROPOSAL-P4 risks.
A26: Strategic and architecture alignment | B26: 1 | C26: ='01 Scoring Model'!$B$12 -> 0.1 | D26: =IF(B26="","",B26*C26) -> 0.1 | E26: Contradicts principle 1 (managed over self-managed) and direction to managed platform services. | F26: R. Alder | G26: TARGET_STATE principle 1 and direction.
A27: Weighted priority score | D27: =IF(COUNT(B20:B26)=0,"",ROUND(SUM(D20:D26),2)) -> 1.95 | E27: Out of 5.00. Compare on '02 Portfolio Summary'.
A29: 3. Scope
A30: In scope | E30: Explicitly out of scope
A31: Cluster build | E31: Database tier
A32: Application refactor | E32: Customer web front end
A33: Migration
A34: Training and handover
A36: 4. Dependencies
A37: Type | B37: Depends on | E37: Nature of the dependency | F37: Owner | G37: Criticality
A38: Internal | B38: P1 Cost visibility | E38: No baseline exists for order-management run cost. P1 would produce it. | F38: Priya Narang | G38: High
A39: Commercial | B39: P3 observability platform | E39: Cluster telemetry would add ingest volume to a consumption-billed platform not in P3's estimate. | F39: Priya Narang | G39: Medium
A40: Resource | B40: Solutions Architect capacity | E40: 1,100 hours is more than available in the period and collides with P2 and P3. | F40: Delivery lead | G40: Critical
A42: 5. Key risks
A43: Risk | B43: Likelihood | C43: Impact | D43: Score | E43: Mitigation | F43: Owner | G43: Response (residual score)
A44: Credentials stored as keys on nodes breach SEC-07 | B44: High | C44: High | D44: 9 | E44: Redesign to managed identity or drop the self-managed design. | F44: Marta Quesnel | G44: Avoid
A45: Architect capacity exceeded: 1,100 hours against 800 available | B45: High | C45: High | D45: 9 | E45: Resequence, split the scope or reduce architect hours before approval. | F45: Tomas Ellery | G45: Mitigate (residual 4)
A46: Team has not run a production cluster | B46: High | C46: Medium | D46: 6 | E46: Managed Kubernetes service or training before approval. | F46: Tomas Ellery | G46: Mitigate (residual 4)
A47: Unknown refactor scope inflates cost | B47: High | C47: High | D47: 9 | E47: Fixed-scope assessment before approval. | F47: L. Hartwell | G47: Mitigate (residual 6)
A48: Likelihood times impact, each 1 to 4 (Low, Medium, High, Critical). Red at 9 or above: needs a named owner and a review date. Optional 6th to 8th items per risk: response, residual likelihood, residual impact.
A50: 6. Success KPIs
A51: KPI | B51: Baseline | D51: Target | E51: Measurement source | F51: Measured by
A52: Order-management run cost per month | B52: TBC, not in finance export | D52: Evidenced reduction | E52: Finance cost export | F52: 60 days after cutover
A53: Release lead time | B53: 14 days (unsourced) | D53: 5 days | E53: Deployment records | F53: 90 days after cutover
A55: 7. EA governance gates
A56: Gate | B56: Status | E56: Evidence or artefact | F56: Reviewer | G56: Date cleared
A57: Alignment with a named business capability | B57: Partial | E57: Order management | F57: R. Alder
A58: Architecture standards compliance | B58: Not met | E58: Contradicts principle 1 and SEC-07 | F58: R. Alder
A59: Security review completed | B59: Not started | E59: Security review not started | F59: Marta Quesnel
A60: Operational ownership defined (named team, not a role) | B60: Not started | E60: Run team after handover not agreed | F60: Tomas Ellery
A61: Success KPIs agreed with a measured baseline | B61: Not met | E61: No cost baseline | F61: Finance
A62: Rollback strategy documented and tested | B62: Not started | E62: Rollback not documented | F62: L. Hartwell
A63: Cost model and payback agreed with FinOps | B63: Not met | E63: Total in deck differs from line items by 15,000; run cost not stated | F63: Finance
A64: Data, retention and privacy position cleared | B64: Not started | E64: Data position not reviewed | F64: Marta Quesnel
A65: Change and CAB approval path confirmed | B65: Not started | E65: Change path not confirmed | F65: PMO
A66: Architecture decision recorded and traceable (ADR or decision log) | B66: Not started | E66: ADR not drafted | F66: R. Alder
A67: Valid statuses: Met, Partial, Not started, Not met, Not applicable.
A69: 8. Open questions
A70: Q1 | B70: What is the run cost baseline of the order-management platform?
A71: Q2 | B71: Why does the deck total (205,000) differ from the line items (220,000)?
A72: Q3 | B72: How will the design meet SEC-07?
A73: Q4 | B73: How can 1,100 architect hours fit in the period?
A75: 9. Traceability and benefits
A76: Business capability or value stream | B76: Order management | E76: Name the capability this changes. Gate 1 depends on it.
A77: Architecture principles addressed | B77: Tests principles 1 and 4; breaches both | E77: Optional. The principles this initiative follows or tests.
A78: Gap closed (baseline to target) | B78: Baseline: managed platform service. Target: self-managed cluster. This moves away from the target state. | E78: One line: where it is today, where it ends up.
A79: Benefits owner (named) | B79: Tomas Ellery, Head of Applications | E79: The person who answers for the benefit after delivery.
A80: Benefits review date | B80: Not set | E80: When the KPIs above are checked against the business case.
A81: Standards references | B81: TOGAF Phase E/F work package; COBIT APO12, APO03 | E81: Optional. TOGAF phase or artefact, COBIT objective IDs.

Sheet P5
A1: P5. Customer portal with an AI assistant
A2: Enterprise Architecture Impact Matrix
A4: 1. Project profile
A5: Project ID | B5: P5
A6: Project name | B6: Customer portal with an AI assistant | E6: Pulled by '02 Portfolio Summary'. Keep it in this cell.
A7: Business sponsor | B7: Joss Penhallow, Marketing Director | E7: Named individual required before EA approval.
A8: Architecture owner | B8: TBC | E8: Named individual required before EA approval.
A9: Delivery owner | B9: TBC | E9: Named individual required before EA approval.
A10: Estimated cost (USD)
A11: Estimated duration (months)
A12: Hard external deadline | B12: None identified.
A13: Current status | B13: Idea, no business case or estimate. Held, not scored.
A14: Recommended wave | B14: Hold | E14: See '03 Sequencing'.
A15: Basis of estimate | B15: PROPOSAL-P5 only. | E15: Cite the document and slide or section.
A17: 2. Weighted impact assessment
A18: Enter 1 to 5 in column B. Anchors are on '01 Scoring Model'. Column C is a link; do not edit it.
A19: Dimension | B19: Score (1-5) | C19: Weight | D19: Weighted | E19: Assessment | F19: Owner | G19: Evidence and basis
A20: Business value | C20: ='01 Scoring Model'!$B$6 -> 0.1 | D20: =IF(B20="","",B20*C20)
A21: Cost optimization and savings | C21: ='01 Scoring Model'!$B$7 -> 0.35 | D21: =IF(B21="","",B21*C21)
A22: Time criticality | C22: ='01 Scoring Model'!$B$8 -> 0.15 | D22: =IF(B22="","",B22*C22)
A23: Risk reduction and resilience | C23: ='01 Scoring Model'!$B$9 -> 0.1 | D23: =IF(B23="","",B23*C23)
A24: Security and compliance | C24: ='01 Scoring Model'!$B$10 -> 0.05 | D24: =IF(B24="","",B24*C24)
A25: Delivery confidence | C25: ='01 Scoring Model'!$B$11 -> 0.15 | D25: =IF(B25="","",B25*C25)
A26: Strategic and architecture alignment | C26: ='01 Scoring Model'!$B$12 -> 0.1 | D26: =IF(B26="","",B26*C26)
A27: Weighted priority score | D27: =IF(COUNT(B20:B26)=0,"",ROUND(SUM(D20:D26),2)) | E27: Out of 5.00. Compare on '02 Portfolio Summary'.
A29: 3. Scope
A30: In scope | E30: Explicitly out of scope
A36: 4. Dependencies
A37: Type | B37: Depends on | E37: Nature of the dependency | F37: Owner | G37: Criticality
A43: 5. Key risks
A44: Risk | B44: Likelihood | C44: Impact | D44: Score | E44: Mitigation | F44: Owner | G44: Response (residual score)
A49: Likelihood times impact, each 1 to 4 (Low, Medium, High, Critical). Red at 9 or above: needs a named owner and a review date. Optional 6th to 8th items per risk: response, residual likelihood, residual impact.
A51: 6. Success KPIs
A52: KPI | B52: Baseline | D52: Target | E52: Measurement source | F52: Measured by
A58: 7. EA governance gates
A59: Gate | B59: Status | E59: Evidence or artefact | F59: Reviewer | G59: Date cleared
A60: Alignment with a named business capability | B60: Not started
A61: Architecture standards compliance | B61: Not started
A62: Security review completed | B62: Not started
A63: Operational ownership defined (named team, not a role) | B63: Not started
A64: Success KPIs agreed with a measured baseline | B64: Not started
A65: Rollback strategy documented and tested | B65: Not started
A66: Cost model and payback agreed with FinOps | B66: Not started
A67: Data, retention and privacy position cleared | B67: Not started
A68: Change and CAB approval path confirmed | B68: Not started
A69: Architecture decision recorded and traceable (ADR or decision log) | B69: Not started
A70: Valid statuses: Met, Partial, Not started, Not met, Not applicable.
A72: 8. Open questions
A73: Q1 | B73: What is the business case and expected benefit?
A74: Q2 | B74: What is the cost, duration and scope?
A75: Q3 | B75: What are the risks, including data and security?
A77: 9. Traceability and benefits
A78: Business capability or value stream | E78: Name the capability this changes. Gate 1 depends on it.
A79: Architecture principles addressed | E79: Optional. The principles this initiative follows or tests.
A80: Gap closed (baseline to target) | E80: One line: where it is today, where it ends up.
A81: Benefits owner (named) | E81: The person who answers for the benefit after delivery.
A82: Benefits review date | E82: When the KPIs above are checked against the business case.
A83: Standards references | E83: Optional. TOGAF phase or artefact, COBIT objective IDs.
